enpacken/__init__.py
enpacken/__main__.py
enpacken-0.1.0a0.dev0.dist-info/LICENSE
enpacken-0.1.0a0.dev0.dist-info/METADATA
enpacken-0.1.0a0.dev0.dist-info/WHEEL
enpacken-0.1.0a0.dev0.dist-info/entry_points.txt
enpacken-0.1.0a0.dev0.dist-info/top_level.txt
enpacken-0.1.0a0.dev0.dist-info/RECORD
